{
    "/js/ajaxComment.js": "/js/ajaxComment.js",
    "/js/ajaxCommentDelete.js": "/js/ajaxCommentDelete.js",
    "/js/ajaxlike.js": "/js/ajaxlike.js",
    "/js/app.js": "/js/app.js",
    "/css/top-page.css": "/css/top-page.css",
    "/css/footer.css": "/css/footer.css",
    "/css/post/create.css": "/css/post/create.css",
    "/css/post/index.css": "/css/post/index.css",
    "/css/post/show.css": "/css/post/show.css",
    "/css/introduction/introduction_show.css": "/css/introduction/introduction_show.css",
    "/css/introduction/introduction_create.css": "/css/introduction/introduction_create.css",
    "/js/cover_image_preview.js": "/js/cover_image_preview.js",
    "/js/imagePreview.js": "/js/imagePreview.js",
    "/js/introduction_pop.js": "/js/introduction_pop.js",
    "/js/profile_image_preview.js": "/js/profile_image_preview.js"
}
